verge_auth_sdk/__init__.py
verge_auth_sdk/helpers.py
verge_auth_sdk/middleware.py
verge_auth_sdk/secret_provider.py
verge_auth_sdk/verge_routes.py
verge_auth_sdk-0.1.81.dist-info/licenses/LICENSE
verge_auth_sdk-0.1.81.dist-info/METADATA
verge_auth_sdk-0.1.81.dist-info/WHEEL
verge_auth_sdk-0.1.81.dist-info/top_level.txt
verge_auth_sdk-0.1.81.dist-info/RECORD
