Metadata-Version: 2.4
Name: verge-auth-sdk
Version: 0.1.81
Summary: Secure centralized authentication SDK for FastAPI microservices
Author-email: Verge Infosoft <contactus@vergeinfosoft.com>
License: MIT
Project-URL: Homepage, https://www.vergeinfosoft.com
Requires-Python: >=3.8
License-File: LICENSE
Requires-Dist: fastapi
Requires-Dist: httpx
Requires-Dist: python-dotenv
Dynamic: license-file
